codeany_hub/__init__.py
codeany_hub/cli.py
codeany_hub/client.py
codeany_hub/config.py
codeany_hub/clients/__init__.py
codeany_hub/clients/base.py
codeany_hub/clients/competitions.py
codeany_hub/clients/hubs.py
codeany_hub/clients/imports.py
codeany_hub/clients/judge.py
codeany_hub/clients/mcq.py
codeany_hub/clients/members.py
codeany_hub/clients/ratings.py
codeany_hub/clients/submissions.py
codeany_hub/clients/tasks.py
codeany_hub/clients/users.py
codeany_hub/core/__init__.py
codeany_hub/core/auth.py
codeany_hub/core/errors.py
codeany_hub/core/pagination.py
codeany_hub/core/poller.py
codeany_hub/core/retry.py
codeany_hub/core/tokens.py
codeany_hub/core/transport.py
codeany_hub/core/versioning.py
codeany_hub/filters/__init__.py
codeany_hub/filters/competitions.py
codeany_hub/filters/submissions.py
codeany_hub/integrations/__init__.py
codeany_hub/integrations/mcp.py
codeany_hub/models/__init__.py
codeany_hub/models/common.py
codeany_hub/models/competition.py
codeany_hub/models/enums.py
codeany_hub/models/hub.py
codeany_hub/models/inputs.py
codeany_hub/models/mcq.py
codeany_hub/models/member.py
codeany_hub/models/rating.py
codeany_hub/models/submission.py
codeany_hub/models/task.py
codeany_hub-0.2.2.12.dist-info/METADATA
codeany_hub-0.2.2.12.dist-info/WHEEL
codeany_hub-0.2.2.12.dist-info/entry_points.txt
codeany_hub-0.2.2.12.dist-info/RECORD
