Metadata-Version: 2.4
Name: codeany-hub
Version: 0.2.2.12
Summary: Python SDK for the Codeany Hub APIs.
Project-URL: Homepage, https://codeany.dev/
Project-URL: Documentation, https://codeany.dev/docs
Project-URL: Repository, https://github.com/codeany/codeany-hub-python
Project-URL: Issues, https://github.com/codeany/codeany-hub-python/issues
Author-email: Codeany <support@codeany.dev>
License: MIT
Requires-Python: >=3.9
Requires-Dist: httpx<0.28,>=0.26.0
Requires-Dist: pydantic<3.0.0,>=2.6.0
Requires-Dist: typing-extensions>=4.7.0
Provides-Extra: dev
Requires-Dist: mypy>=1.8.0; extra == 'dev'
Requires-Dist: pytest-asyncio>=0.23.0; extra == 'dev'
Requires-Dist: pytest-httpx>=0.30.0; extra == 'dev'
Requires-Dist: pytest>=8.0.0; extra == 'dev'
Requires-Dist: ruff>=0.3.0; extra == 'dev'
